pybiwenger/__init__.py
pybiwenger/endpoints/__init__.py
pybiwenger/endpoints/endpoints.py
pybiwenger/scripts/bulk_load_player_market_history.py
pybiwenger/scripts/bulk_load_player_points_history.py
pybiwenger/src/__init__.py
pybiwenger/src/biwenger/__init__.py
pybiwenger/src/biwenger/league.py
pybiwenger/src/biwenger/market.py
pybiwenger/src/biwenger/players.py
pybiwenger/src/client/__init__.py
pybiwenger/src/client/client.py
pybiwenger/src/client/urls.py
pybiwenger/types/__init__.py
pybiwenger/types/account.py
pybiwenger/types/player.py
pybiwenger/types/user.py
pybiwenger/utils/__init__.py
pybiwenger/utils/exporting.py
pybiwenger/utils/log.py
pybiwenger/utils/parsing.py
pybiwenger-1.3.0.dist-info/METADATA
pybiwenger-1.3.0.dist-info/WHEEL
pybiwenger-1.3.0.dist-info/RECORD
